
Command_Line>>> javap -c DataMean

Compiled from DataMean.java
public synchronized class DataMean extends java.lang.Object
    /* ACC_SUPER bit set */
{
    public static void main(java.lang.String[]);
    public DataMean();
}

Method void main(java.lang.String[])
   0 sipush 10000
   3 istore_3
   4 new #10 <Class java.util.Random>
   7 dup
   8 invokespecial #12 <Method java.util.Random()>
  11 astore_1
  12 dconst_0
  13 dstore 4
  15 iconst_1
  16 istore_2
  17 goto 32
  20 dload 4
  22 aload_1
  23 invokevirtual #17 <Method double nextDouble()>
  26 dadd
  27 dstore 4
  29 iinc 2 1
  32 iload_2
  33 iload_3
  34 if_icmplt 20
  37 dload 4
  39 iload_3
  40 i2d      
  41 ddiv
  42 dstore 4
  44 getstatic #18 <Field java.io.PrintStream out>
  47 new #8 <Class java.lang.StringBuffer>
  50 dup
  51 ldc #2 <String " The mean of ">
  53 invokespecial #13 <Method java.lang.StringBuffer(java.lang.String)>
  56 iload_3
  57 invokevirtual #15 <Method java.lang.StringBuffer append(int)>
  60 ldc #4 <String " random numbers
">
  62 invokevirtual #16 <Method java.lang.StringBuffer append(java.lang.String)>
  65 ldc #3 <String " between 0 and 1 is ">
  67 invokevirtual #16 <Method java.lang.StringBuffer append(java.lang.String)>
  70 dload 4
  72 invokevirtual #14 <Method java.lang.StringBuffer append(double)>
  75 ldc #1 <String " !">
  77 invokevirtual #16 <Method java.lang.StringBuffer append(java.lang.String)>
  80 invokevirtual #20 <Method java.lang.String toString()>
  83 invokevirtual #19 <Method void println(java.lang.String)>
  86 return

Method DataMean()
   0 aload_0
   1 invokespecial #11 <Method java.lang.Object()>
   4 return

